rembglib/__init__.py
rembglib/_version.py
rembglib/bg.py
rembglib/session_base.py
rembglib/session_cloth.py
rembglib/session_factory.py
rembglib/session_simple.py
rembglib-0.1.0.dist-info/LICENSE.txt
rembglib-0.1.0.dist-info/WHEEL
rembglib-0.1.0.dist-info/METADATA
rembglib-0.1.0.dist-info/RECORD
