Metadata-Version: 2.1
Name: rembglib
Version: 0.1.0
Summary: 
Author: Alejandro P. Hall
Author-email: alejandro.polvillo@myrealfood.app
Requires-Python: >=3.9,<3.10
Classifier: Programming Language :: Python :: 3
Classifier: Programming Language :: Python :: 3.9
Requires-Dist: Pillow (>=9.2.0,<10.0.0)
Requires-Dist: PyMatting (>=1.1.8,<2.0.0)
Requires-Dist: gdown (>=4.5.1,<5.0.0)
Requires-Dist: onnxruntime (>=1.12.1,<2.0.0)
Requires-Dist: opencv-python (>=4.6.0,<5.0.0)
Requires-Dist: scipy (>=1.9.0,<2.0.0)
